schemarquify/__init__.py
schemarquify/data.py
schemarquify/exceptions.py
schemarquify/main.py
schemarquify/schemas.py
schemarquify/serializers.py
schemarquify/test.py
schemarquify/validators.py
schemarquify-0.0.1.dist-info/METADATA
schemarquify-0.0.1.dist-info/WHEEL
schemarquify-0.0.1.dist-info/top_level.txt
schemarquify-0.0.1.dist-info/RECORD
