Metadata-Version: 2.1
Name: schemarquify
Version: 0.0.1
Summary: Tokko Forms flavor.
Home-page: https://github.com/JoseSalgado1024/schemarquify
Author: El Jose Salgado
Author-email: jsalgado@tokko.com
License: MIT License
Platform: UNKNOWN
Classifier: Intended Audience :: Developers
Classifier: License :: OSI Approved :: MIT License
Classifier: Operating System :: OS Independent
Classifier: Programming Language :: Python
Classifier: Programming Language :: Python :: 3.8
Classifier: Topic :: Internet :: WWW/HTTP
Classifier: Topic :: Internet :: WWW/HTTP :: Dynamic Content
